tracarbon/__init__.py
tracarbon/__main__.py
tracarbon/builder.py
tracarbon/conf.py
tracarbon/exceptions.py
tracarbon/general_metrics.py
tracarbon/py.typed
tracarbon/cli/__init__.py
tracarbon/emissions/__init__.py
tracarbon/emissions/carbon_emissions.py
tracarbon/exporters/__init__.py
tracarbon/exporters/datadog_exporter.py
tracarbon/exporters/exporter.py
tracarbon/exporters/json_exporter.py
tracarbon/exporters/prometheus_exporter.py
tracarbon/exporters/stdout.py
tracarbon/hardwares/__init__.py
tracarbon/hardwares/amd_rapl.py
tracarbon/hardwares/cloud_providers.py
tracarbon/hardwares/containers.py
tracarbon/hardwares/energy.py
tracarbon/hardwares/gpu.py
tracarbon/hardwares/hardware.py
tracarbon/hardwares/rapl.py
tracarbon/hardwares/sensors.py
tracarbon/hardwares/data/__init__.py
tracarbon/locations/__init__.py
tracarbon/locations/country.py
tracarbon/locations/location.py
tracarbon/locations/data/__init__.py
tracarbon-0.9.1.dist-info/licenses/LICENSE.txt
tracarbon-0.9.1.dist-info/METADATA
tracarbon-0.9.1.dist-info/WHEEL
tracarbon-0.9.1.dist-info/entry_points.txt
tracarbon-0.9.1.dist-info/top_level.txt
tracarbon-0.9.1.dist-info/RECORD
