Metadata-Version: 2.4
Name: tracarbon
Version: 0.9.1
Summary: Tracarbon is a Python library that tracks your device's energy consumption and calculates your carbon emissions.
Author-email: Florian Valeye <fvaleye@github.com>
License-Expression: Apache-2.0
Project-URL: documentation, https://fvaleye.github.io
Project-URL: repository, https://github.com/fvaleye/tracarbon
Keywords: energy,sustainability,energy-consumption,electricity-consumption,energy-efficiency,carbon-footprint,carbon-emissions
Classifier: Development Status :: 3 - Alpha
Classifier: Programming Language :: Python :: 3 :: Only
Requires-Python: >=3.9
License-File: LICENSE.txt
Requires-Dist: loguru<0.8,>=0.6
Requires-Dist: aiohttp<4.0.0,>=3.9.3
Requires-Dist: aiocache<0.13.0,>=0.12.1
Requires-Dist: aiofiles<26.0,>=23.2
Requires-Dist: psutil>=5.9.8
Requires-Dist: orjson<4,>=3.10
Requires-Dist: msgpack<2.0.0,>=1.1.1
Requires-Dist: pydantic<3.0.0,>=1.10.7
Requires-Dist: typer<0.22,>=0.7
Requires-Dist: ec2-metadata<3.0.0,>=2.14.0
Requires-Dist: python-dotenv<1.3,>=0.21
Requires-Dist: asyncer<0.0.13,>=0.0.5
Provides-Extra: datadog
Requires-Dist: datadog<0.53,>=0.44; extra == "datadog"
Provides-Extra: prometheus
Requires-Dist: prometheus-client<0.24,>=0.16; extra == "prometheus"
Provides-Extra: kubernetes
Requires-Dist: kubernetes<35.0,>=26.1; extra == "kubernetes"
Provides-Extra: dev
Requires-Dist: ty>=0.0.1a6; extra == "dev"
Requires-Dist: ruff<0.15.0,>=0.11.13; extra == "dev"
Requires-Dist: pytest<9.0.0,>=8.4.0; extra == "dev"
Requires-Dist: pytest-mock<4.0.0,>=3.14.0; extra == "dev"
Requires-Dist: pytest-asyncio<1.3.0,>=0.24.0; extra == "dev"
Requires-Dist: pytest-cov<8.0.0,>=5.0.0; extra == "dev"
Requires-Dist: pytest-xdist<4.0.0,>=3.6.1; extra == "dev"
Requires-Dist: pytest-clarity<2.0.0,>=1.0.1; extra == "dev"
Requires-Dist: sphinx<8.0.0,>=7.4.7; extra == "dev"
Requires-Dist: pydata-sphinx-theme<0.17.0,>=0.14.4; extra == "dev"
Requires-Dist: toml<0.11.0,>=0.10.2; extra == "dev"
Requires-Dist: datadog<0.53,>=0.44; extra == "dev"
Requires-Dist: prometheus-client<0.24,>=0.16; extra == "dev"
Requires-Dist: bandit<2.0.0,>=1.7.9; extra == "dev"
Requires-Dist: radon<7.0.0,>=6.0.1; extra == "dev"
Requires-Dist: kubernetes<35.0,>=26.1; extra == "dev"
Requires-Dist: autodoc_pydantic==2.2.0; extra == "dev"
Requires-Dist: uv; extra == "dev"
Requires-Dist: pre-commit<5.0.0,>=3.7.0; extra == "dev"
Provides-Extra: all
Requires-Dist: tracarbon[datadog]; extra == "all"
Requires-Dist: tracarbon[prometheus]; extra == "all"
Requires-Dist: tracarbon[kubernetes]; extra == "all"
Dynamic: license-file
